<?xml version="1.0" encoding="UTF-8" standalone="yes"?>
<QTelescopeParts>
	<SiTypes>
		<doubleSiTypes>
			<doubleSi id="DoubleSi_DSD_L">
				<doubleSiSize doubleSiX="6.3" doubleSiY="6.3" doubleSiZ="0.1"/>
				<doubleSiSensAreaSize doubleSiSensX="5.8" doubleSiSensY="5.8" doubleSiSensZ="0.1"/>
				<deadLayerThicknessFrontSide>0.000199</deadLayerThicknessFrontSide>
				<deadLayerThicknessBackSide>0.00025</deadLayerThicknessBackSide>
				<stripCountX>16</stripCountX>
				<stripCountY>16</stripCountY>
				<doubleSiMedia>silicon</doubleSiMedia>
			</doubleSi>
		</doubleSiTypes>
		<singleSiTypes>
			<singleSi id="SingleSi_SSD20_1">
				<singleSiSize singleSiX="5" singleSiY="5" singleSiZ="0.002"/>
				<singleSiSensAreaSize singleSiSensX="5" singleSiSensY="5" singleSiSensZ="0.002"/>
				<deadLayerThicknessFrontSide>0.0000585</deadLayerThicknessFrontSide>
				<deadLayerThicknessBackSide>0.000086</deadLayerThicknessBackSide>
				<stripCount>16</stripCount>
				<singleSiMedia>silicon</singleSiMedia>
			</singleSi>	
			<singleSi id="SingleSi_SSD_1">
				<singleSiSize singleSiX="6" singleSiY="6" singleSiZ="0.1"/>
				<singleSiSensAreaSize singleSiSensX="6" singleSiSensY="6" singleSiSensZ="0.1"/>
				<deadLayerThicknessFrontSide>0.0001946</deadLayerThicknessFrontSide>
				<deadLayerThicknessBackSide>0.0001946</deadLayerThicknessBackSide>
				<stripCount>16</stripCount>
				<singleSiMedia>silicon</singleSiMedia>
			</singleSi>
			<singleSi id="SingleSi_SSD20_2">
				<singleSiSize singleSiX="5" singleSiY="5" singleSiZ="0.002"/>
				<singleSiSensAreaSize singleSiSensX="5" singleSiSensY="5" singleSiSensZ="0.002"/>
				<deadLayerThicknessFrontSide>0.000074</deadLayerThicknessFrontSide>
				<deadLayerThicknessBackSide>0.000086</deadLayerThicknessBackSide>
				<stripCount>16</stripCount>
				<singleSiMedia>silicon</singleSiMedia>
			</singleSi>	
			<singleSi id="SingleSi_SSD_2">
				<singleSiSize singleSiX="6" singleSiY="6" singleSiZ="0.1"/>
				<singleSiSensAreaSize singleSiSensX="6" singleSiSensY="6" singleSiSensZ="0.1"/>
				<deadLayerThicknessFrontSide>0.000195</deadLayerThicknessFrontSide>
				<deadLayerThicknessBackSide>0.000195</deadLayerThicknessBackSide>
				<stripCount>16</stripCount>
				<singleSiMedia>silicon</singleSiMedia>
			</singleSi>
		</singleSiTypes>
	</SiTypes>
	<CsITypes>
		<CsI id="CsI_C">
 			<CsISize CsIX="1.65" CsIY="1.65" CsIZ="5"/>
 			<cubesCountX>4</cubesCountX>			
 			<cubesCountY>4</cubesCountY>
 			<splitSize>0.01</splitSize>
 			<deadLayer>0.002</deadLayer>
			<CsIMedia>CsI</CsIMedia>
		</CsI>
	</CsITypes>
</QTelescopeParts>


